executor_script_interface/__init__.py
executor_script_interface/script_functions.py
executor_script_interface/version.py
executor_script_interface-0.0.2.dist-info/LICENSE
executor_script_interface-0.0.2.dist-info/METADATA
executor_script_interface-0.0.2.dist-info/WHEEL
executor_script_interface-0.0.2.dist-info/top_level.txt
executor_script_interface-0.0.2.dist-info/RECORD
