Metadata-Version: 2.1
Name: executor-script-interface
Version: 0.0.2
Summary: Scripting interface for NilarTestExecutor
Home-page: https://www.nilar.com
Author: Nilar Software Engineering
Author-email: softwarengineering@nilar.com
License: UNKNOWN
Platform: UNKNOWN
Classifier: Development Status :: 1 - Planning
Classifier: Intended Audience :: Developers
Classifier: Programming Language :: Python :: 3
Classifier: Operating System :: Unix
Classifier: License :: OSI Approved :: MIT License
Requires-Python: >=3.5
